{
  "yojo": [
    {
      "id": "0",
      "name": "かがり",
      "type": "幼女",
      "fruit": "いちご",
      "description": "",
      "imageUrl": "/images/yojo/111イチゴかがり.png",
      "cost": 0,
      "hp": 0,
      "attack": 0
    },
    {
      "id": "1",
      "name": "とここ",
      "type": "幼女",
      "fruit": "いちご",
      "description": "",
      "imageUrl": "/images/yojo/111イチゴとここ.png",
      "cost": 0,
      "hp": 0,
      "attack": 0
    },
    {
      "id": "2",
      "name": "うゆち",
      "type": "幼女",
      "fruit": "いちご",
      "description": "",
      "imageUrl": "/images/yojo/111イチゴうゆち.png",
      "cost": 0,
      "hp": 0,
      "attack": 0
    },
    {
      "id": "3",
      "name": "うぃまる",
      "type": "幼女",
      "fruit": "いちご",
      "description": "",
      "imageUrl": "/images/yojo/213イチゴうぃまる.png",
      "cost": 0,
      "hp": 0,
      "attack": 0
    },
    {
      "id": "4",
      "name": "えーりん",
      "type": "幼女",
      "fruit": "いちご",
      "description": "",
      "imageUrl": "/images/yojo/221イチゴえーりん.png",
      "cost": 0,
      "hp": 0,
      "attack": 0
    },
    {
      "id": "5",
      "name": "かんらん",
      "type": "幼女",
      "fruit": "いちご",
      "description": "",
      "imageUrl": "/images/yojo/221イチゴかんらん改.png",
      "cost": 0,
      "hp": 0,
      "attack": 0
    },
    {
      "id": "6",
      "name": "ほーずき",
      "type": "幼女",
      "fruit": "いちご",
      "description": "",
      "imageUrl": "/images/yojo/212イチゴほーずき.png",
      "cost": 0,
      "hp": 0,
      "attack": 0
    },
    {
      "id": "7",
      "name": "レンテ",
      "type": "幼女",
      "fruit": "いちご",
      "description": "",
      "imageUrl": "/images/yojo/222イチゴレンテ.png",
      "cost": 0,
      "hp": 0,
      "attack": 0
    },
    {
      "id": "8",
      "name": "ちょり",
      "type": "幼女",
      "fruit": "いちご",
      "description": "",
      "imageUrl": "/images/yojo/211イチゴちょり.png",
      "cost": 0,
      "hp": 0,
      "attack": 0
    },
    {
      "id": "9",
      "name": "ぷらむ",
      "type": "幼女",
      "fruit": "いちご",
      "description": "",
      "imageUrl": "/images/yojo/212イチゴぷらむ.png",
      "cost": 0,
      "hp": 0,
      "attack": 0
    },
    {
      "id": "10",
      "name": "ゼロオレ",
      "type": "幼女",
      "fruit": "いちご",
      "description": "",
      "imageUrl": "/images/yojo/222イチゴゼロオレンジ.png",
      "cost": 0,
      "hp": 0,
      "attack": 0
    },
    {
      "id": "11",
      "name": "もなか",
      "type": "幼女",
      "fruit": "いちご",
      "description": "",
      "imageUrl": "/images/yojo/233イチゴもなか改.png",
      "cost": 0,
      "hp": 0,
      "attack": 0
    },
    {
      "id": "12",
      "name": "あみの",
      "type": "幼女",
      "fruit": "いちご",
      "description": "",
      "imageUrl": "/images/yojo/311イチゴあみの.png",
      "cost": 0,
      "hp": 0,
      "attack": 0
    },
    {
      "id": "13",
      "name": "がと",
      "type": "幼女",
      "fruit": "いちご",
      "description": "",
      "imageUrl": "/images/yojo/321イチゴがと.png",
      "cost": 0,
      "hp": 0,
      "attack": 0
    },
    {
      "id": "14",
      "name": "ももか",
      "type": "幼女",
      "fruit": "いちご",
      "description": "",
      "imageUrl": "/images/yojo/322イチゴももか.png",
      "cost": 0,
      "hp": 0,
      "attack": 0
    },
    {
      "id": "15",
      "name": "まこぽに",
      "type": "幼女",
      "fruit": "いちご",
      "description": "",
      "imageUrl": "/images/yojo/322イチゴまこぽに.png",
      "cost": 0,
      "hp": 0,
      "attack": 0
    },
    {
      "id": "16",
      "name": "いのむー",
      "type": "幼女",
      "fruit": "いちご",
      "description": "",
      "imageUrl": "/images/yojo/323イチゴいのむー.png",
      "cost": 0,
      "hp": 0,
      "attack": 0
    },
    {
      "id": "17",
      "name": "まめろん",
      "type": "幼女",
      "fruit": "いちご",
      "description": "",
      "imageUrl": "/images/yojo/334イチゴまめろん.png",
      "cost": 0,
      "hp": 0,
      "attack": 0
    },
    {
      "id": "18",
      "name": "ぎってぃ",
      "type": "幼女",
      "fruit": "いちご",
      "description": "",
      "imageUrl": "/images/yojo/433イチゴぎってぃ.png",
      "cost": 0,
      "hp": 0,
      "attack": 0
    },
    {
      "id": "19",
      "name": "さら",
      "type": "幼女",
      "fruit": "いちご",
      "description": "",
      "imageUrl": "/images/yojo/423イチゴさら.png",
      "cost": 0,
      "hp": 0,
      "attack": 0
    },
    {
      "id": "20",
      "name": "ふろんとさん",
      "type": "幼女",
      "fruit": "いちご",
      "description": "",
      "imageUrl": "/images/yojo/433イチゴふろんとさん.png",
      "cost": 0,
      "hp": 0,
      "attack": 0
    },
    {
      "id": "21",
      "name": "しゅお",
      "type": "幼女",
      "fruit": "いちご",
      "description": "",
      "imageUrl": "/images/yojo/442イチゴしゅお.png",
      "cost": 0,
      "hp": 0,
      "attack": 0
    },
    {
      "id": "22",
      "name": "ゆうひ",
      "type": "幼女",
      "fruit": "いちご",
      "description": "",
      "imageUrl": "/images/yojo/424イチゴゆうひ.png",
      "cost": 0,
      "hp": 0,
      "attack": 0
    },
    {
      "id": "23",
      "name": "ふらら",
      "type": "幼女",
      "fruit": "いちご",
      "description": "",
      "imageUrl": "/images/yojo/434イチゴふらら.png",
      "cost": 0,
      "hp": 0,
      "attack": 0
    },
    {
      "id": "24",
      "name": "りくす",
      "type": "幼女",
      "fruit": "いちご",
      "description": "",
      "imageUrl": "/images/yojo/536イチゴりくす改.png",
      "cost": 0,
      "hp": 0,
      "attack": 0
    },
    {
      "id": "25",
      "name": "ストラ",
      "type": "幼女",
      "fruit": "いちご",
      "description": "",
      "imageUrl": "/images/yojo/533イチゴストラ.png",
      "cost": 0,
      "hp": 0,
      "attack": 0
    },
    {
      "id": "26",
      "name": "しゅれい",
      "type": "幼女",
      "fruit": "いちご",
      "description": "",
      "imageUrl": "/images/yojo/523イチゴしゅれい.png",
      "cost": 0,
      "hp": 0,
      "attack": 0
    },
    {
      "id": "27",
      "name": "オフティ二",
      "type": "幼女",
      "fruit": "いちご",
      "description": "",
      "imageUrl": "/images/yojo/544イチゴオフティ二.png",
      "cost": 0,
      "hp": 0,
      "attack": 0
    },
    {
      "id": "28",
      "name": "じょんこ",
      "type": "幼女",
      "fruit": "いちご",
      "description": "",
      "imageUrl": "/images/yojo/655イチゴじょんこ.png",
      "cost": 0,
      "hp": 0,
      "attack": 0
    },
    {
      "id": "29",
      "name": "いろは",
      "type": "幼女",
      "fruit": "いちご",
      "description": "",
      "imageUrl": "/images/yojo/735イチゴいろは.png",
      "cost": 0,
      "hp": 0,
      "attack": 0
    },
    {
      "id": "30",
      "name": "みゅーとん",
      "type": "幼女",
      "fruit": "いちご",
      "description": "",
      "imageUrl": "/images/yojo/735イチゴみゅーとん.png",
      "cost": 0,
      "hp": 0,
      "attack": 0
    },
    {
      "id": "31",
      "name": "ほーずき",
      "type": "幼女",
      "fruit": "ぶどう",
      "description": "",
      "imageUrl": "/images/yojo/111ぶどうほーずき.png",
      "cost": 0,
      "hp": 0,
      "attack": 0
    },
    {
      "id": "32",
      "name": "ぷらむ",
      "type": "幼女",
      "fruit": "ぶどう",
      "description": "",
      "imageUrl": "/images/yojo/111ぶどうぷらむ.png",
      "cost": 0,
      "hp": 0,
      "attack": 0
    },
    {
      "id": "33",
      "name": "りんね",
      "type": "幼女",
      "fruit": "ぶどう",
      "description": "",
      "imageUrl": "/images/yojo/33.png",
      "cost": 0,
      "hp": 0,
      "attack": 0
    },
    {
      "id": "34",
      "name": "とここ",
      "type": "幼女",
      "fruit": "ぶどう",
      "description": "",
      "imageUrl": "/images/yojo/111ぶどうとここ.png",
      "cost": 0,
      "hp": 0,
      "attack": 0
    },
    {
      "id": "35",
      "name": "えーりん",
      "type": "幼女",
      "fruit": "ぶどう",
      "description": "",
      "imageUrl": "/images/yojo/221ぶどうえーりん.png",
      "cost": 0,
      "hp": 0,
      "attack": 0
    },
    {
      "id": "36",
      "name": "ふらら",
      "type": "幼女",
      "fruit": "ぶどう",
      "description": "",
      "imageUrl": "/images/yojo/211ぶどうふらら.png",
      "cost": 0,
      "hp": 0,
      "attack": 0
    },
    {
      "id": "37",
      "name": "がと",
      "type": "幼女",
      "fruit": "ぶどう",
      "description": "",
      "imageUrl": "/images/yojo/222ぶどうがと.png",
      "cost": 0,
      "hp": 0,
      "attack": 0
    },
    {
      "id": "38",
      "name": "氷花",
      "type": "幼女",
      "fruit": "ぶどう",
      "description": "",
      "imageUrl": "/images/yojo/221ぶどう氷花.png",
      "cost": 0,
      "hp": 0,
      "attack": 0
    },
    {
      "id": "39",
      "name": "かがり",
      "type": "幼女",
      "fruit": "ぶどう",
      "description": "",
      "imageUrl": "/images/yojo/212ぶどうかがり.png",
      "cost": 0,
      "hp": 0,
      "attack": 0
    },
    {
      "id": "40",
      "name": "りくす",
      "type": "幼女",
      "fruit": "ぶどう",
      "description": "",
      "imageUrl": "/images/yojo/222ぶどうりくす.png",
      "cost": 0,
      "hp": 0,
      "attack": 0
    },
    {
      "id": "41",
      "name": "さら",
      "type": "幼女",
      "fruit": "ぶどう",
      "description": "",
      "imageUrl": "/images/yojo/222ぶどうさら.png",
      "cost": 0,
      "hp": 0,
      "attack": 0
    },
    {
      "id": "42",
      "name": "うゆち",
      "type": "幼女",
      "fruit": "ぶどう",
      "description": "",
      "imageUrl": "/images/yojo/210ぶどううゆち.png",
      "cost": 0,
      "hp": 0,
      "attack": 0
    },
    {
      "id": "43",
      "name": "ちょり",
      "type": "幼女",
      "fruit": "ぶどう",
      "description": "",
      "imageUrl": "/images/yojo/322ぶどうちょり.png",
      "cost": 0,
      "hp": 0,
      "attack": 0
    },
    {
      "id": "44",
      "name": "いのむー",
      "type": "幼女",
      "fruit": "ぶどう",
      "description": "",
      "imageUrl": "/images/yojo/323ぶどういのむー.png",
      "cost": 0,
      "hp": 0,
      "attack": 0
    },
    {
      "id": "45",
      "name": "まこぽに",
      "type": "幼女",
      "fruit": "ぶどう",
      "description": "",
      "imageUrl": "/images/yojo/332ぶどうまこぽに.png",
      "cost": 0,
      "hp": 0,
      "attack": 0
    },
    {
      "id": "46",
      "name": "ももか",
      "type": "幼女",
      "fruit": "ぶどう",
      "description": "",
      "imageUrl": "/images/yojo/322ぶどうももか.png",
      "cost": 0,
      "hp": 0,
      "attack": 0
    },
    {
      "id": "47",
      "name": "ゆうひ",
      "type": "幼女",
      "fruit": "ぶどう",
      "description": "",
      "imageUrl": "/images/yojo/317ぶどうゆうひ.png",
      "cost": 0,
      "hp": 0,
      "attack": 0
    },
    {
      "id": "48",
      "name": "ゼロオレ",
      "type": "幼女",
      "fruit": "ぶどう",
      "description": "",
      "imageUrl": "/images/yojo/322ぶどうゼロオレンジ.png",
      "cost": 0,
      "hp": 0,
      "attack": 0
    },
    {
      "id": "49",
      "name": "ふろんとさん",
      "type": "幼女",
      "fruit": "ぶどう",
      "description": "",
      "imageUrl": "/images/yojo/415ぶどうふろんとさん.png",
      "cost": 0,
      "hp": 0,
      "attack": 0
    },
    {
      "id": "50",
      "name": "もなか",
      "type": "幼女",
      "fruit": "ぶどう",
      "description": "",
      "imageUrl": "/images/yojo/465ぶどうもなか.png",
      "cost": 0,
      "hp": 0,
      "attack": 0
    },
    {
      "id": "51",
      "name": "オフティ二",
      "type": "幼女",
      "fruit": "ぶどう",
      "description": "",
      "imageUrl": "/images/yojo/434ぶどうオフティ二.png",
      "cost": 0,
      "hp": 0,
      "attack": 0
    },
    {
      "id": "52",
      "name": "レンテ",
      "type": "幼女",
      "fruit": "ぶどう",
      "description": "",
      "imageUrl": "/images/yojo/433ぶどうレンテ.png",
      "cost": 0,
      "hp": 0,
      "attack": 0
    },
    {
      "id": "53",
      "name": "しゅれい",
      "type": "幼女",
      "fruit": "ぶどう",
      "description": "",
      "imageUrl": "/images/yojo/433ぶどうしゅれい.png",
      "cost": 0,
      "hp": 0,
      "attack": 0
    },
    {
      "id": "54",
      "name": "しゅお",
      "type": "幼女",
      "fruit": "ぶどう",
      "description": "",
      "imageUrl": "/images/yojo/433ぶどうしゅお改.png",
      "cost": 0,
      "hp": 0,
      "attack": 0
    },
    {
      "id": "55",
      "name": "あみの",
      "type": "幼女",
      "fruit": "ぶどう",
      "description": "",
      "imageUrl": "/images/yojo/542ぶどうあみの.png",
      "cost": 0,
      "hp": 0,
      "attack": 0
    },
    {
      "id": "56",
      "name": "ぎってぃ",
      "type": "幼女",
      "fruit": "ぶどう",
      "description": "",
      "imageUrl": "/images/yojo/534ぶどうぎってぃ.png",
      "cost": 0,
      "hp": 0,
      "attack": 0
    },
    {
      "id": "57",
      "name": "かんらん",
      "type": "幼女",
      "fruit": "ぶどう",
      "description": "",
      "imageUrl": "/images/yojo/533ぶどうかんらん.png",
      "cost": 0,
      "hp": 0,
      "attack": 0
    },
    {
      "id": "58",
      "name": "まめろん",
      "type": "幼女",
      "fruit": "ぶどう",
      "description": "",
      "imageUrl": "/images/yojo/544ぶどうまめろん.png",
      "cost": 0,
      "hp": 0,
      "attack": 0
    },
    {
      "id": "59",
      "name": "ストラ",
      "type": "幼女",
      "fruit": "ぶどう",
      "description": "",
      "imageUrl": "/images/yojo/504ぶどうストラ.png",
      "cost": 0,
      "hp": 0,
      "attack": 0
    },
    {
      "id": "60",
      "name": "レンス",
      "type": "幼女",
      "fruit": "ぶどう",
      "description": "",
      "imageUrl": "/images/yojo/643ぶどうレンス.png",
      "cost": 0,
      "hp": 0,
      "attack": 0
    },
    {
      "id": "61",
      "name": "いろは",
      "type": "幼女",
      "fruit": "ぶどう",
      "description": "",
      "imageUrl": "/images/yojo/755ぶどういろは.png",
      "cost": 0,
      "hp": 0,
      "attack": 0
    },
    {
      "id": "62",
      "name": "じょんこ",
      "type": "幼女",
      "fruit": "ぶどう",
      "description": "",
      "imageUrl": "/images/yojo/766ぶどうじょんこ.png",
      "cost": 0,
      "hp": 0,
      "attack": 0
    },
    {
      "id": "63",
      "name": "みゅーとん",
      "type": "幼女",
      "fruit": "ぶどう",
      "description": "",
      "imageUrl": "/images/yojo/755ぶどうみゅーとん改.png",
      "cost": 0,
      "hp": 0,
      "attack": 0
    },
    {
      "id": "64",
      "name": "うぃまる",
      "type": "幼女",
      "fruit": "ぶどう",
      "description": "",
      "imageUrl": "/images/yojo/711ぶどううぃまる.png",
      "cost": 0,
      "hp": 0,
      "attack": 0
    }
  ]
}